{
"meta":{"test_sets":[],"test_metrics":[],"learn_metrics":[{"best_value":"Min","name":"RMSE"}],"launch_mode":"Train","parameters":"","iteration_count":100,"learn_sets":["learn"],"name":"experiment"},
"iterations":[
{"learn":[13.96962521],"iteration":0,"passed_time":0.001861680896,"remaining_time":0.1843064087},
{"learn":[13.09082657],"iteration":1,"passed_time":0.003854149424,"remaining_time":0.1888533218},
{"learn":[12.27861651],"iteration":2,"passed_time":0.005060359419,"remaining_time":0.1636182879},
{"learn":[11.53029884],"iteration":3,"passed_time":0.006005406448,"remaining_time":0.1441297547},
{"learn":[10.87492512],"iteration":4,"passed_time":0.007091683114,"remaining_time":0.1347419792},
{"learn":[10.38155225],"iteration":5,"passed_time":0.008609607503,"remaining_time":0.1348838509},
{"learn":[9.857621344],"iteration":6,"passed_time":0.009558105543,"remaining_time":0.1269862594},
{"learn":[9.411181059],"iteration":7,"passed_time":0.01126272815,"remaining_time":0.1295213737},
{"learn":[8.998198398],"iteration":8,"passed_time":0.01322024171,"remaining_time":0.1336713329},
{"learn":[8.588034504],"iteration":9,"passed_time":0.01466818745,"remaining_time":0.1320136871},
{"learn":[8.232135915],"iteration":10,"passed_time":0.01685723852,"remaining_time":0.1363903844},
{"learn":[7.936645968],"iteration":11,"passed_time":0.01846557204,"remaining_time":0.1354141949},
{"learn":[7.686327869],"iteration":12,"passed_time":0.02000232762,"remaining_time":0.133861731},
{"learn":[7.453139483],"iteration":13,"passed_time":0.02171588626,"remaining_time":0.133397587},
{"learn":[7.216574456],"iteration":14,"passed_time":0.02279222074,"remaining_time":0.1291559175},
{"learn":[7.018377399],"iteration":15,"passed_time":0.02375131413,"remaining_time":0.1246943992},
{"learn":[6.823313325],"iteration":16,"passed_time":0.02644977533,"remaining_time":0.1291371384},
{"learn":[6.666946823],"iteration":17,"passed_time":0.02820027593,"remaining_time":0.1284679237},
{"learn":[6.508910347],"iteration":18,"passed_time":0.02988299246,"remaining_time":0.1273959152},
{"learn":[6.386746007],"iteration":19,"passed_time":0.03166584331,"remaining_time":0.1266633732},
{"learn":[6.265973887],"iteration":20,"passed_time":0.03290502345,"remaining_time":0.1237855644},
{"learn":[6.169088554],"iteration":21,"passed_time":0.03437035011,"remaining_time":0.121858514},
{"learn":[6.063254647],"iteration":22,"passed_time":0.03550059951,"remaining_time":0.1188498331},
{"learn":[5.976012341],"iteration":23,"passed_time":0.03674288708,"remaining_time":0.1163524757},
{"learn":[5.901135024],"iteration":24,"passed_time":0.03806118805,"remaining_time":0.1141835641},
{"learn":[5.835939901],"iteration":25,"passed_time":0.03967673607,"remaining_time":0.112926095},
{"learn":[5.775227205],"iteration":26,"passed_time":0.04178363265,"remaining_time":0.1129705624},
{"learn":[5.723443194],"iteration":27,"passed_time":0.04377702632,"remaining_time":0.1125694963},
{"learn":[5.680032138],"iteration":28,"passed_time":0.04689847336,"remaining_time":0.1148204003},
{"learn":[5.627248312],"iteration":29,"passed_time":0.04809884463,"remaining_time":0.1122306375},
{"learn":[5.592690321],"iteration":30,"passed_time":0.04956890187,"remaining_time":0.1103307816},
{"learn":[5.544273978],"iteration":31,"passed_time":0.05087283966,"remaining_time":0.1081047843},
{"learn":[5.503344158],"iteration":32,"passed_time":0.05274162438,"remaining_time":0.1070814798},
{"learn":[5.478259921],"iteration":33,"passed_time":0.05388923228,"remaining_time":0.1046085097},
{"learn":[5.442185155],"iteration":34,"passed_time":0.05559041256,"remaining_time":0.1032393376},
{"learn":[5.407844279],"iteration":35,"passed_time":0.05735892698,"remaining_time":0.1019714257},
{"learn":[5.383507306],"iteration":36,"passed_time":0.05908793018,"remaining_time":0.1006091784},
{"learn":[5.362378839],"iteration":37,"passed_time":0.06163751397,"remaining_time":0.1005664702},
{"learn":[5.340630083],"iteration":38,"passed_time":0.06304155063,"remaining_time":0.09860345098},
{"learn":[5.318674311],"iteration":39,"passed_time":0.06474920327,"remaining_time":0.0971238049},
{"learn":[5.302066897],"iteration":40,"passed_time":0.06662993887,"remaining_time":0.09588210715},
{"learn":[5.284928558],"iteration":41,"passed_time":0.06830665537,"remaining_time":0.09432823837},
{"learn":[5.272330995],"iteration":42,"passed_time":0.07033875086,"remaining_time":0.09323973951},
{"learn":[5.261014227],"iteration":43,"passed_time":0.07179253388,"remaining_time":0.09137231585},
{"learn":[5.229469639],"iteration":44,"passed_time":0.07307752763,"remaining_time":0.08931697822},
{"learn":[5.215020572],"iteration":45,"passed_time":0.07443258539,"remaining_time":0.08737738284},
{"learn":[5.193062414],"iteration":46,"passed_time":0.07641538153,"remaining_time":0.08617053662},
{"learn":[5.180484848],"iteration":47,"passed_time":0.0775478559,"remaining_time":0.08401017722},
{"learn":[5.165159502],"iteration":48,"passed_time":0.07971893942,"remaining_time":0.08297277368},
{"learn":[5.141982763],"iteration":49,"passed_time":0.08157751795,"remaining_time":0.08157751795},
{"learn":[5.131085119],"iteration":50,"passed_time":0.08345514612,"remaining_time":0.0801823953},
{"learn":[5.115896901],"iteration":51,"passed_time":0.0851161837,"remaining_time":0.07856878496},
{"learn":[5.102227813],"iteration":52,"passed_time":0.08627762603,"remaining_time":0.07651034761},
{"learn":[5.092694221],"iteration":53,"passed_time":0.08716319428,"remaining_time":0.07425012846},
{"learn":[5.084135611],"iteration":54,"passed_time":0.08819590178,"remaining_time":0.07216028327},
{"learn":[5.067392027],"iteration":55,"passed_time":0.08977512702,"remaining_time":0.0705375998},
{"learn":[5.05548496],"iteration":56,"passed_time":0.09187066224,"remaining_time":0.06930593818},
{"learn":[5.037754059],"iteration":57,"passed_time":0.0939241054,"remaining_time":0.06801400736},
{"learn":[5.018441657],"iteration":58,"passed_time":0.09651141523,"remaining_time":0.06706725465},
{"learn":[5.009952596],"iteration":59,"passed_time":0.09754616397,"remaining_time":0.06503077598},
{"learn":[5.000684433],"iteration":60,"passed_time":0.09863392708,"remaining_time":0.06306103535},
{"learn":[4.982819001],"iteration":61,"passed_time":0.09970318522,"remaining_time":0.06110840384},
{"learn":[4.966552282],"iteration":62,"passed_time":0.1005626904,"remaining_time":0.0590606277},
{"learn":[4.948387795],"iteration":63,"passed_time":0.1014299164,"remaining_time":0.05705432799},
{"learn":[4.933079332],"iteration":64,"passed_time":0.1029139079,"remaining_time":0.05541518119},
{"learn":[4.923067166],"iteration":65,"passed_time":0.1050535135,"remaining_time":0.05411847667},
{"learn":[4.91587203],"iteration":66,"passed_time":0.1070947577,"remaining_time":0.05274816425},
{"learn":[4.906625327],"iteration":67,"passed_time":0.1088302861,"remaining_time":0.05121425227},
{"learn":[4.895848666],"iteration":68,"passed_time":0.1108409731,"remaining_time":0.04979811837},
{"learn":[4.886562569],"iteration":69,"passed_time":0.112634266,"remaining_time":0.04827182828},
{"learn":[4.876525557],"iteration":70,"passed_time":0.1136042231,"remaining_time":0.04640172493},
{"learn":[4.866771122],"iteration":71,"passed_time":0.1145519819,"remaining_time":0.04454799296},
{"learn":[4.860489381],"iteration":72,"passed_time":0.1155883024,"remaining_time":0.04275183789},
{"learn":[4.846895943],"iteration":73,"passed_time":0.1169894277,"remaining_time":0.04110439351},
{"learn":[4.830532583],"iteration":74,"passed_time":0.1184864941,"remaining_time":0.03949549803},
{"learn":[4.818616331],"iteration":75,"passed_time":0.1217650652,"remaining_time":0.03845212587},
{"learn":[4.806132466],"iteration":76,"passed_time":0.1235576232,"remaining_time":0.03690682251},
{"learn":[4.800479202],"iteration":77,"passed_time":0.1253969901,"remaining_time":0.03536838181},
{"learn":[4.797819002],"iteration":78,"passed_time":0.1261205025,"remaining_time":0.0335257032},
{"learn":[4.786614428],"iteration":79,"passed_time":0.127236856,"remaining_time":0.031809214},
{"learn":[4.777804595],"iteration":80,"passed_time":0.1282356371,"remaining_time":0.03007996426},
{"learn":[4.767203373],"iteration":81,"passed_time":0.129411201,"remaining_time":0.02840733681},
{"learn":[4.752577047],"iteration":82,"passed_time":0.1304610992,"remaining_time":0.02672094803},
{"learn":[4.743678884],"iteration":83,"passed_time":0.1317100487,"remaining_time":0.02508762832},
{"learn":[4.737404981],"iteration":84,"passed_time":0.1332851169,"remaining_time":0.02352090299},
{"learn":[4.728022428],"iteration":85,"passed_time":0.1354340202,"remaining_time":0.02204739864},
{"learn":[4.723347156],"iteration":86,"passed_time":0.1376006365,"remaining_time":0.02056101464},
{"learn":[4.717517757],"iteration":87,"passed_time":0.1398753776,"remaining_time":0.01907391513},
{"learn":[4.709503034],"iteration":88,"passed_time":0.1409528275,"remaining_time":0.01742113598},
{"learn":[4.703039995],"iteration":89,"passed_time":0.1418799873,"remaining_time":0.01576444303},
{"learn":[4.696059284],"iteration":90,"passed_time":0.1428992387,"remaining_time":0.01413289174},
{"learn":[4.686066202],"iteration":91,"passed_time":0.1438447342,"remaining_time":0.01250823775},
{"learn":[4.674543063],"iteration":92,"passed_time":0.1453735006,"remaining_time":0.01094209144},
{"learn":[4.671858724],"iteration":93,"passed_time":0.1471868051,"remaining_time":0.009394902452},
{"learn":[4.6586434],"iteration":94,"passed_time":0.1492063356,"remaining_time":0.007852965031},
{"learn":[4.650850795],"iteration":95,"passed_time":0.1510953497,"remaining_time":0.006295639571},
{"learn":[4.647951816],"iteration":96,"passed_time":0.1534667301,"remaining_time":0.004746393714},
{"learn":[4.636294688],"iteration":97,"passed_time":0.1547455827,"remaining_time":0.003158073117},
{"learn":[4.629521481],"iteration":98,"passed_time":0.1556680944,"remaining_time":0.001572404994},
{"learn":[4.625948565],"iteration":99,"passed_time":0.1565468894,"remaining_time":0}
]}